tox_recreate/__init__.py
tox_recreate/plugin.py
tox_recreate-0.0.6.dist-info/licenses/LICENSE
tox_recreate-0.0.6.dist-info/METADATA
tox_recreate-0.0.6.dist-info/WHEEL
tox_recreate-0.0.6.dist-info/entry_points.txt
tox_recreate-0.0.6.dist-info/top_level.txt
tox_recreate-0.0.6.dist-info/RECORD
