Metadata-Version: 2.4
Name: tox-recreate
Version: 0.0.6
Summary: Recreate tox virtual environments when `pyproject.toml`, `setup.cfg` or `setup.py` change.
Project-URL: Repository, https://github.com/hypothesis/tox-recreate
Project-URL: Issues, https://github.com/hypothesis/tox-recreate/issues
Project-URL: Changelog, https://github.com/hypothesis/tox-recreate/releases
Classifier: Programming Language :: Python :: 3
Classifier: License :: OSI Approved :: BSD License
Classifier: Intended Audience :: Developers
Requires-Python: >=3.9
License-File: LICENSE
Dynamic: license-file
